README.rst
setup.py
egrp365/__init__.py
egrp365/api.py
egrp365.egg-info/PKG-INFO
egrp365.egg-info/SOURCES.txt
egrp365.egg-info/dependency_links.txt
egrp365.egg-info/requires.txt
egrp365.egg-info/top_level.txt