Metadata-Version: 1.0
Name: egrp365
Version: 0.0.4
Summary: This module implements the egrp365.ru HTTP API.
Home-page: https://github.com/egrp365/python-egrp365-api
Author: egrp365
Author-email: mail@egrp365.ru
License: MIT License (MIT)
Platform: UNKNOWN
